pyscaleio/__init__.py
pyscaleio/client.py
pyscaleio/config.py
pyscaleio/constants.py
pyscaleio/exceptions.py
pyscaleio/manager.py
pyscaleio/models.py
pyscaleio/utils.py
pyscaleio-0.1.7.dist-info/METADATA
pyscaleio-0.1.7.dist-info/RECORD
pyscaleio-0.1.7.dist-info/WHEEL
pyscaleio-0.1.7.dist-info/pbr.json
pyscaleio-0.1.7.dist-info/top_level.txt
