Metadata-Version: 2.1
Name: pyscaleio
Version: 0.1.7
Summary: ScaleIO/VxFlex API client
Home-page: https://github.com/gmmephisto/pyscaleio
Author: Mikhail Ushanov
Author-email: gm.mephisto@gmail.com
License: Apache Software License 2.0
Keywords: emc
Requires-Dist: inflection (==0.3.1)
Requires-Dist: object-validator (==0.1.6)
Requires-Dist: psys (==0.4)
Requires-Dist: requests (>=2.3)
Requires-Dist: six (==1.10.0)
